script_scheduler/__init__.py
script_scheduler/scheduler_ui.py
ui_pytask_manager-0.1.1.dist-info/METADATA
ui_pytask_manager-0.1.1.dist-info/WHEEL
ui_pytask_manager-0.1.1.dist-info/entry_points.txt
ui_pytask_manager-0.1.1.dist-info/top_level.txt
ui_pytask_manager-0.1.1.dist-info/RECORD
